{
  "country": "Burkina Faso",
  "data": [
    {
      "day": "2020-01-01",
      "daily_deaths": 0
    },
    {
      "day": "2020-02-01",
      "daily_deaths": 0
    },
    {
      "day": "2020-03-01",
      "daily_deaths": 0.6029324326664209
    },
    {
      "day": "2020-04-01",
      "daily_deaths": 1.262984782923013
    },
    {
      "day": "2020-05-01",
      "daily_deaths": 0.4886926128529012
    },
    {
      "day": "2020-06-01",
      "daily_deaths": 0
    },
    {
      "day": "2020-07-01",
      "daily_deaths": 0
    },
    {
      "day": "2020-08-01",
      "daily_deaths": 0.08885320369154215
    },
    {
      "day": "2020-09-01",
      "daily_deaths": 0.0761598888784647
    },
    {
      "day": "2020-10-01",
      "daily_deaths": 0.4442660142667592
    },
    {
      "day": "2020-11-01",
      "daily_deaths": 0.05711991665884853
    },
    {
      "day": "2020-12-01",
      "daily_deaths": 0.5013859267346561
    },
    {
      "day": "2021-01-01",
      "daily_deaths": 1.7770640440285206
    },
    {
      "day": "2021-02-01",
      "daily_deaths": 0.9837318840436636
    },
    {
      "day": "2021-03-01",
      "daily_deaths": 0.19039972219616172
    },
    {
      "day": "2021-04-01",
      "daily_deaths": 0.4823459559120238
    },
    {
      "day": "2021-05-01",
      "daily_deaths": 0.418879380915314
    },
    {
      "day": "2021-06-01",
      "daily_deaths": 0.08885320369154215
    },
    {
      "day": "2021-07-01",
      "daily_deaths": 0.044426601845771074
    },
    {
      "day": "2021-08-01",
      "daily_deaths": 0.08885320369154215
    },
    {
      "day": "2021-09-01",
      "daily_deaths": 0.4823459521867335
    },
    {
      "day": "2021-10-01",
      "daily_deaths": 1.5168510880321264
    },
    {
      "day": "2021-11-01",
      "daily_deaths": 2.9511956684291363
    },
    {
      "day": "2021-12-01",
      "daily_deaths": 1.5676243309862912
    },
    {
      "day": "2022-01-01",
      "daily_deaths": 2.0943969106301665
    },
    {
      "day": "2022-02-01",
      "daily_deaths": 0.45061266236007214
    },
    {
      "day": "2022-03-01",
      "daily_deaths": 0.2538662916049361
    },
    {
      "day": "2022-04-01",
      "daily_deaths": 0.13962646154686809
    },
    {
      "day": "2022-05-01",
      "daily_deaths": 0.006346657406538725
    },
    {
      "day": "2022-06-01",
      "daily_deaths": 0.1332798022776842
    },
    {
      "day": "2022-07-01",
      "daily_deaths": 0
    },
    {
      "day": "2022-08-01",
      "daily_deaths": 0
    },
    {
      "day": "2022-09-01",
      "daily_deaths": 0
    },
    {
      "day": "2022-10-01",
      "daily_deaths": 0
    },
    {
      "day": "2022-11-01",
      "daily_deaths": 0
    },
    {
      "day": "2022-12-01",
      "daily_deaths": 0.3554128147661686
    },
    {
      "day": "2023-01-01",
      "daily_deaths": 0.044426601845771074
    },
    {
      "day": "2023-02-01",
      "daily_deaths": 0
    },
    {
      "day": "2023-03-01",
      "daily_deaths": 0
    },
    {
      "day": "2023-04-01",
      "daily_deaths": 0
    },
    {
      "day": "2023-05-01",
      "daily_deaths": 0
    },
    {
      "day": "2023-06-01",
      "daily_deaths": 0
    },
    {
      "day": "2023-07-01",
      "daily_deaths": 0
    },
    {
      "day": "2023-08-01",
      "daily_deaths": 0
    },
    {
      "day": "2023-09-01",
      "daily_deaths": 0
    },
    {
      "day": "2023-10-01",
      "daily_deaths": 0
    },
    {
      "day": "2023-11-01",
      "daily_deaths": 0.13327980553731322
    },
    {
      "day": "2023-12-01",
      "daily_deaths": 0.044426601845771074
    },
    {
      "day": "2024-01-01",
      "daily_deaths": 0
    },
    {
      "day": "2024-02-01",
      "daily_deaths": 0
    },
    {
      "day": "2024-03-01",
      "daily_deaths": 0
    },
    {
      "day": "2024-04-01",
      "daily_deaths": 0
    },
    {
      "day": "2024-05-01",
      "daily_deaths": 0
    },
    {
      "day": "2024-06-01",
      "daily_deaths": 0
    },
    {
      "day": "2024-07-01",
      "daily_deaths": 0
    },
    {
      "day": "2024-08-01",
      "daily_deaths": 0
    },
    {
      "day": "2024-09-01",
      "daily_deaths": 0
    },
    {
      "day": "2024-10-01",
      "daily_deaths": 0
    },
    {
      "day": "2024-11-01",
      "daily_deaths": 0
    },
    {
      "day": "2024-12-01",
      "daily_deaths": 0
    },
    {
      "day": "2025-01-01",
      "daily_deaths": 0
    },
    {
      "day": "2025-02-01",
      "daily_deaths": 0
    },
    {
      "day": "2025-03-01",
      "daily_deaths": 0
    }
  ]
}