{
  "country": "Guinea",
  "data": [
    {
      "day": "2020-01-01",
      "daily_deaths": 0
    },
    {
      "day": "2020-02-01",
      "daily_deaths": 0
    },
    {
      "day": "2020-03-01",
      "daily_deaths": 0
    },
    {
      "day": "2020-04-01",
      "daily_deaths": 0.5488588213920593
    },
    {
      "day": "2020-05-01",
      "daily_deaths": 0.9554209113121032
    },
    {
      "day": "2020-06-01",
      "daily_deaths": 0.6098431348800659
    },
    {
      "day": "2020-07-01",
      "daily_deaths": 1.036733329296112
    },
    {
      "day": "2020-08-01",
      "daily_deaths": 0.9554209113121032
    },
    {
      "day": "2020-09-01",
      "daily_deaths": 0.5590228736400604
    },
    {
      "day": "2020-10-01",
      "daily_deaths": 0.3963980376720429
    },
    {
      "day": "2020-11-01",
      "daily_deaths": 0.33541372418403625
    },
    {
      "day": "2020-12-01",
      "daily_deaths": 0.30492156744003296
    },
    {
      "day": "2021-01-01",
      "daily_deaths": 0.12196862697601318
    },
    {
      "day": "2021-02-01",
      "daily_deaths": 0.41672614216804493
    },
    {
      "day": "2021-03-01",
      "daily_deaths": 2.276747703552246
    },
    {
      "day": "2021-04-01",
      "daily_deaths": 1.555099993944168
    },
    {
      "day": "2021-05-01",
      "daily_deaths": 1.3619830012321472
    },
    {
      "day": "2021-06-01",
      "daily_deaths": 0.5996790826320648
    },
    {
      "day": "2021-07-01",
      "daily_deaths": 3.069543778896332
    },
    {
      "day": "2021-08-01",
      "daily_deaths": 8.354850947856903
    },
    {
      "day": "2021-09-01",
      "daily_deaths": 3.435449659824372
    },
    {
      "day": "2021-10-01",
      "daily_deaths": 0.4980385601520538
    },
    {
      "day": "2021-11-01",
      "daily_deaths": 0.14229673147201538
    },
    {
      "day": "2021-12-01",
      "daily_deaths": 0.203281044960022
    },
    {
      "day": "2022-01-01",
      "daily_deaths": 1.860021561384201
    },
    {
      "day": "2022-02-01",
      "daily_deaths": 1.7075607776641846
    },
    {
      "day": "2022-03-01",
      "daily_deaths": 0
    },
    {
      "day": "2022-04-01",
      "daily_deaths": 0.14229673147201538
    },
    {
      "day": "2022-05-01",
      "daily_deaths": 0
    },
    {
      "day": "2022-06-01",
      "daily_deaths": 0.07114836573600769
    },
    {
      "day": "2022-07-01",
      "daily_deaths": 0.14229673147201538
    },
    {
      "day": "2022-08-01",
      "daily_deaths": 0.2439372539520264
    },
    {
      "day": "2022-09-01",
      "daily_deaths": 0.4268901944160461
    },
    {
      "day": "2022-10-01",
      "daily_deaths": 0.25410130620002747
    },
    {
      "day": "2022-11-01",
      "daily_deaths": 0.4980385601520538
    },
    {
      "day": "2022-12-01",
      "daily_deaths": 0.13213267922401428
    },
    {
      "day": "2023-01-01",
      "daily_deaths": 0.0101640522480011
    },
    {
      "day": "2023-02-01",
      "daily_deaths": 0
    },
    {
      "day": "2023-03-01",
      "daily_deaths": 0
    },
    {
      "day": "2023-04-01",
      "daily_deaths": 0.07114836573600769
    },
    {
      "day": "2023-05-01",
      "daily_deaths": 0
    },
    {
      "day": "2023-06-01",
      "daily_deaths": 0
    },
    {
      "day": "2023-07-01",
      "daily_deaths": 0
    },
    {
      "day": "2023-08-01",
      "daily_deaths": 0
    },
    {
      "day": "2023-09-01",
      "daily_deaths": 0
    },
    {
      "day": "2023-10-01",
      "daily_deaths": 0
    },
    {
      "day": "2023-11-01",
      "daily_deaths": 0
    },
    {
      "day": "2023-12-01",
      "daily_deaths": 0
    },
    {
      "day": "2024-01-01",
      "daily_deaths": 0
    },
    {
      "day": "2024-02-01",
      "daily_deaths": 0
    },
    {
      "day": "2024-03-01",
      "daily_deaths": 0
    },
    {
      "day": "2024-04-01",
      "daily_deaths": 0
    },
    {
      "day": "2024-05-01",
      "daily_deaths": 0
    },
    {
      "day": "2024-06-01",
      "daily_deaths": 0
    },
    {
      "day": "2024-07-01",
      "daily_deaths": 0
    },
    {
      "day": "2024-08-01",
      "daily_deaths": 0
    },
    {
      "day": "2024-09-01",
      "daily_deaths": 0
    },
    {
      "day": "2024-10-01",
      "daily_deaths": 0
    },
    {
      "day": "2024-11-01",
      "daily_deaths": 0
    },
    {
      "day": "2024-12-01",
      "daily_deaths": 0
    },
    {
      "day": "2025-01-01",
      "daily_deaths": 0
    },
    {
      "day": "2025-02-01",
      "daily_deaths": 0
    },
    {
      "day": "2025-03-01",
      "daily_deaths": 0
    }
  ]
}