{
  "country": "Mauritania",
  "data": [
    {
      "day": "2020-01-01",
      "daily_deaths": 0
    },
    {
      "day": "2020-02-01",
      "daily_deaths": 0
    },
    {
      "day": "2020-03-01",
      "daily_deaths": 4.36572265625
    },
    {
      "day": "2020-04-01",
      "daily_deaths": 26.1943359375
    },
    {
      "day": "2020-05-01",
      "daily_deaths": 2.900715172290802
    },
    {
      "day": "2020-06-01",
      "daily_deaths": 21.56491267681122
    },
    {
      "day": "2020-07-01",
      "daily_deaths": 7.354338467121124
    },
    {
      "day": "2020-08-01",
      "daily_deaths": 0.41020214557647705
    },
    {
      "day": "2020-09-01",
      "daily_deaths": 0.3809019923210144
    },
    {
      "day": "2020-10-01",
      "daily_deaths": 0
    },
    {
      "day": "2020-11-01",
      "daily_deaths": 1.318506896495819
    },
    {
      "day": "2020-12-01",
      "daily_deaths": 4.98102605342865
    },
    {
      "day": "2021-01-01",
      "daily_deaths": 16.408085823059082
    },
    {
      "day": "2021-02-01",
      "daily_deaths": 3.867620229721069
    },
    {
      "day": "2021-03-01",
      "daily_deaths": 2.138911187648773
    },
    {
      "day": "2021-04-01",
      "daily_deaths": 1.3478070497512815
    },
    {
      "day": "2021-05-01",
      "daily_deaths": 1.4357075095176697
    },
    {
      "day": "2021-06-01",
      "daily_deaths": 4.863825440406799
    },
    {
      "day": "2021-07-01",
      "daily_deaths": 11.83726191520691
    },
    {
      "day": "2021-08-01",
      "daily_deaths": 31.468364357948303
    },
    {
      "day": "2021-09-01",
      "daily_deaths": 15.118879079818726
    },
    {
      "day": "2021-10-01",
      "daily_deaths": 4.658724367618561
    },
    {
      "day": "2021-11-01",
      "daily_deaths": 7.061336934566498
    },
    {
      "day": "2021-12-01",
      "daily_deaths": 7.119937241077423
    },
    {
      "day": "2022-01-01",
      "daily_deaths": 16.29088521003723
    },
    {
      "day": "2022-02-01",
      "daily_deaths": 7.442238926887512
    },
    {
      "day": "2022-03-01",
      "daily_deaths": 0.8204042911529541
    },
    {
      "day": "2022-04-01",
      "daily_deaths": 0.05860030651092529
    },
    {
      "day": "2022-05-01",
      "daily_deaths": 0
    },
    {
      "day": "2022-06-01",
      "daily_deaths": 0
    },
    {
      "day": "2022-07-01",
      "daily_deaths": 1.7580091953277588
    },
    {
      "day": "2022-08-01",
      "daily_deaths": 0.29300153255462646
    },
    {
      "day": "2022-09-01",
      "daily_deaths": 0.4395022988319397
    },
    {
      "day": "2022-10-01",
      "daily_deaths": 0.5860030651092529
    },
    {
      "day": "2022-11-01",
      "daily_deaths": 0
    },
    {
      "day": "2022-12-01",
      "daily_deaths": 0
    },
    {
      "day": "2023-01-01",
      "daily_deaths": 0
    },
    {
      "day": "2023-02-01",
      "daily_deaths": 0
    },
    {
      "day": "2023-03-01",
      "daily_deaths": 0
    },
    {
      "day": "2023-04-01",
      "daily_deaths": 0
    },
    {
      "day": "2023-05-01",
      "daily_deaths": 0
    },
    {
      "day": "2023-06-01",
      "daily_deaths": 0
    },
    {
      "day": "2023-07-01",
      "daily_deaths": 0
    },
    {
      "day": "2023-08-01",
      "daily_deaths": 0
    },
    {
      "day": "2023-09-01",
      "daily_deaths": 0
    },
    {
      "day": "2023-10-01",
      "daily_deaths": 0
    },
    {
      "day": "2023-11-01",
      "daily_deaths": 0
    },
    {
      "day": "2023-12-01",
      "daily_deaths": 0
    },
    {
      "day": "2024-01-01",
      "daily_deaths": 0
    },
    {
      "day": "2024-02-01",
      "daily_deaths": 0
    },
    {
      "day": "2024-03-01",
      "daily_deaths": 0
    },
    {
      "day": "2024-04-01",
      "daily_deaths": 0
    },
    {
      "day": "2024-05-01",
      "daily_deaths": 0
    },
    {
      "day": "2024-06-01",
      "daily_deaths": 0
    },
    {
      "day": "2024-07-01",
      "daily_deaths": 0
    },
    {
      "day": "2024-08-01",
      "daily_deaths": 0
    },
    {
      "day": "2024-09-01",
      "daily_deaths": 0
    },
    {
      "day": "2024-10-01",
      "daily_deaths": 0
    },
    {
      "day": "2024-11-01",
      "daily_deaths": 0
    },
    {
      "day": "2024-12-01",
      "daily_deaths": 0
    },
    {
      "day": "2025-01-01",
      "daily_deaths": 0
    },
    {
      "day": "2025-02-01",
      "daily_deaths": 0
    },
    {
      "day": "2025-03-01",
      "daily_deaths": 0
    }
  ]
}