{
  "country": "Netherlands",
  "data": [
    {
      "day": "2020-01-01",
      "daily_deaths": 0
    },
    {
      "day": "2020-02-01",
      "daily_deaths": 0
    },
    {
      "day": "2020-03-01",
      "daily_deaths": 37.78795157372952
    },
    {
      "day": "2020-04-01",
      "daily_deaths": 227.31814336776733
    },
    {
      "day": "2020-05-01",
      "daily_deaths": 68.66619729995728
    },
    {
      "day": "2020-06-01",
      "daily_deaths": 11.122551627457142
    },
    {
      "day": "2020-07-01",
      "daily_deaths": 2.1144017688930035
    },
    {
      "day": "2020-08-01",
      "daily_deaths": 4.1649726666510105
    },
    {
      "day": "2020-09-01",
      "daily_deaths": 8.010790452361107
    },
    {
      "day": "2020-10-01",
      "daily_deaths": 54.62337678670883
    },
    {
      "day": "2020-11-01",
      "daily_deaths": 111.7042510509491
    },
    {
      "day": "2020-12-01",
      "daily_deaths": 108.97547221183775
    },
    {
      "day": "2021-01-01",
      "daily_deaths": 146.77139973640442
    },
    {
      "day": "2021-02-01",
      "daily_deaths": 89.78627896308899
    },
    {
      "day": "2021-03-01",
      "daily_deaths": 51.70310974121094
    },
    {
      "day": "2021-04-01",
      "daily_deaths": 34.67619073390961
    },
    {
      "day": "2021-05-01",
      "daily_deaths": 27.0962592959404
    },
    {
      "day": "2021-06-01",
      "daily_deaths": 7.444290176033974
    },
    {
      "day": "2021-07-01",
      "daily_deaths": 3.486768275499344
    },
    {
      "day": "2021-08-01",
      "daily_deaths": 10.356579661369324
    },
    {
      "day": "2021-09-01",
      "daily_deaths": 9.36719910800457
    },
    {
      "day": "2021-10-01",
      "daily_deaths": 11.62522055208683
    },
    {
      "day": "2021-11-01",
      "daily_deaths": 57.20853304862976
    },
    {
      "day": "2021-12-01",
      "daily_deaths": 85.27023410797119
    },
    {
      "day": "2022-01-01",
      "daily_deaths": 21.159975707530972
    },
    {
      "day": "2022-02-01",
      "daily_deaths": 17.409905046224594
    },
    {
      "day": "2022-03-01",
      "daily_deaths": 20.30623686313629
    },
    {
      "day": "2022-04-01",
      "daily_deaths": 13.88324210047722
    },
    {
      "day": "2022-05-01",
      "daily_deaths": 4.284655809402466
    },
    {
      "day": "2022-06-01",
      "daily_deaths": 2.553239993751049
    },
    {
      "day": "2022-07-01",
      "daily_deaths": 6.933642461895943
    },
    {
      "day": "2022-08-01",
      "daily_deaths": 6.606508418917656
    },
    {
      "day": "2022-09-01",
      "daily_deaths": 2.8245217204093933
    },
    {
      "day": "2022-10-01",
      "daily_deaths": 9.08793842047453
    },
    {
      "day": "2022-11-01",
      "daily_deaths": 4.978817947208881
    },
    {
      "day": "2022-12-01",
      "daily_deaths": 3.9495431035757065
    },
    {
      "day": "2023-01-01",
      "daily_deaths": 0.5585212633013725
    },
    {
      "day": "2023-02-01",
      "daily_deaths": 0
    },
    {
      "day": "2023-03-01",
      "daily_deaths": 0
    },
    {
      "day": "2023-04-01",
      "daily_deaths": 0
    },
    {
      "day": "2023-05-01",
      "daily_deaths": 0
    },
    {
      "day": "2023-06-01",
      "daily_deaths": 0
    },
    {
      "day": "2023-07-01",
      "daily_deaths": 0
    },
    {
      "day": "2023-08-01",
      "daily_deaths": 0
    },
    {
      "day": "2023-09-01",
      "daily_deaths": 0
    },
    {
      "day": "2023-10-01",
      "daily_deaths": 0
    },
    {
      "day": "2023-11-01",
      "daily_deaths": 0
    },
    {
      "day": "2023-12-01",
      "daily_deaths": 0
    },
    {
      "day": "2024-01-01",
      "daily_deaths": 0
    },
    {
      "day": "2024-02-01",
      "daily_deaths": 0
    },
    {
      "day": "2024-03-01",
      "daily_deaths": 0
    },
    {
      "day": "2024-04-01",
      "daily_deaths": 0
    },
    {
      "day": "2024-05-01",
      "daily_deaths": 0
    },
    {
      "day": "2024-06-01",
      "daily_deaths": 0
    },
    {
      "day": "2024-07-01",
      "daily_deaths": 0
    },
    {
      "day": "2024-08-01",
      "daily_deaths": 0
    },
    {
      "day": "2024-09-01",
      "daily_deaths": 0
    },
    {
      "day": "2024-10-01",
      "daily_deaths": 0
    },
    {
      "day": "2024-11-01",
      "daily_deaths": 0
    },
    {
      "day": "2024-12-01",
      "daily_deaths": 0
    },
    {
      "day": "2025-01-01",
      "daily_deaths": 0
    },
    {
      "day": "2025-02-01",
      "daily_deaths": 0
    },
    {
      "day": "2025-03-01",
      "daily_deaths": 0
    }
  ]
}