{
  "country": "Qatar",
  "data": [
    {
      "day": "2020-01-01",
      "daily_deaths": 0
    },
    {
      "day": "2020-02-01",
      "daily_deaths": 0
    },
    {
      "day": "2020-03-01",
      "daily_deaths": 0.14816823229193687
    },
    {
      "day": "2020-04-01",
      "daily_deaths": 3.3090905658900738
    },
    {
      "day": "2020-05-01",
      "daily_deaths": 7.013296343386173
    },
    {
      "day": "2020-06-01",
      "daily_deaths": 26.620892643928528
    },
    {
      "day": "2020-07-01",
      "daily_deaths": 20.447216123342518
    },
    {
      "day": "2020-08-01",
      "daily_deaths": 9.927271611988544
    },
    {
      "day": "2020-09-01",
      "daily_deaths": 6.223065793514252
    },
    {
      "day": "2020-10-01",
      "daily_deaths": 5.926729328930378
    },
    {
      "day": "2020-11-01",
      "daily_deaths": 2.2225234918296337
    },
    {
      "day": "2020-12-01",
      "daily_deaths": 2.5682493671774864
    },
    {
      "day": "2021-01-01",
      "daily_deaths": 1.333514090627432
    },
    {
      "day": "2021-02-01",
      "daily_deaths": 3.062143463641405
    },
    {
      "day": "2021-03-01",
      "daily_deaths": 9.186430402100086
    },
    {
      "day": "2021-04-01",
      "daily_deaths": 51.76010221242905
    },
    {
      "day": "2021-05-01",
      "daily_deaths": 40.89443254470825
    },
    {
      "day": "2021-06-01",
      "daily_deaths": 12.495521008968351
    },
    {
      "day": "2021-07-01",
      "daily_deaths": 4.445046946406364
    },
    {
      "day": "2021-08-01",
      "daily_deaths": 0.39511528611183167
    },
    {
      "day": "2021-09-01",
      "daily_deaths": 1.037177626043558
    },
    {
      "day": "2021-10-01",
      "daily_deaths": 1.6298505552113056
    },
    {
      "day": "2021-11-01",
      "daily_deaths": 0.5926729291677475
    },
    {
      "day": "2021-12-01",
      "daily_deaths": 1.5310717448592186
    },
    {
      "day": "2022-01-01",
      "daily_deaths": 8.593757539987564
    },
    {
      "day": "2022-02-01",
      "daily_deaths": 8.346810430288315
    },
    {
      "day": "2022-03-01",
      "daily_deaths": 4.34626816958189
    },
    {
      "day": "2022-04-01",
      "daily_deaths": 0
    },
    {
      "day": "2022-05-01",
      "daily_deaths": 0
    },
    {
      "day": "2022-06-01",
      "daily_deaths": 0.5432835184037685
    },
    {
      "day": "2022-07-01",
      "daily_deaths": 0.5432835184037685
    },
    {
      "day": "2022-08-01",
      "daily_deaths": 0.2963364645838737
    },
    {
      "day": "2022-09-01",
      "daily_deaths": 0.3457258753478527
    },
    {
      "day": "2022-10-01",
      "daily_deaths": 0.6914517506957054
    },
    {
      "day": "2022-11-01",
      "daily_deaths": 0.2469470538198948
    },
    {
      "day": "2022-12-01",
      "daily_deaths": 0.09877882152795792
    },
    {
      "day": "2023-01-01",
      "daily_deaths": 0.3457258753478527
    },
    {
      "day": "2023-02-01",
      "daily_deaths": 0
    },
    {
      "day": "2023-03-01",
      "daily_deaths": 0.6914517506957054
    },
    {
      "day": "2023-04-01",
      "daily_deaths": 0.6914517506957054
    },
    {
      "day": "2023-05-01",
      "daily_deaths": 0
    },
    {
      "day": "2023-06-01",
      "daily_deaths": 0
    },
    {
      "day": "2023-07-01",
      "daily_deaths": 0
    },
    {
      "day": "2023-08-01",
      "daily_deaths": 0
    },
    {
      "day": "2023-09-01",
      "daily_deaths": 0
    },
    {
      "day": "2023-10-01",
      "daily_deaths": 0
    },
    {
      "day": "2023-11-01",
      "daily_deaths": 0
    },
    {
      "day": "2023-12-01",
      "daily_deaths": 0
    },
    {
      "day": "2024-01-01",
      "daily_deaths": 0
    },
    {
      "day": "2024-02-01",
      "daily_deaths": 0
    },
    {
      "day": "2024-03-01",
      "daily_deaths": 0
    },
    {
      "day": "2024-04-01",
      "daily_deaths": 0
    },
    {
      "day": "2024-05-01",
      "daily_deaths": 0
    },
    {
      "day": "2024-06-01",
      "daily_deaths": 0
    },
    {
      "day": "2024-07-01",
      "daily_deaths": 0
    },
    {
      "day": "2024-08-01",
      "daily_deaths": 0
    },
    {
      "day": "2024-09-01",
      "daily_deaths": 0
    },
    {
      "day": "2024-10-01",
      "daily_deaths": 0
    },
    {
      "day": "2024-11-01",
      "daily_deaths": 0
    },
    {
      "day": "2024-12-01",
      "daily_deaths": 0
    },
    {
      "day": "2025-01-01",
      "daily_deaths": 0
    },
    {
      "day": "2025-02-01",
      "daily_deaths": 0
    },
    {
      "day": "2025-03-01",
      "daily_deaths": 0
    }
  ]
}